nes_emulator_py.libs/libgcc_s-a3a07607.so.1
nes_emulator_py.libs/libstdc++-496613c0.so.6.0.32
nes_emulator_py-9.0.0.dist-info/entry_points.txt
nes_emulator_py-9.0.0.dist-info/METADATA
nes_emulator_py-9.0.0.dist-info/RECORD
nes_emulator_py-9.0.0.dist-info/top_level.txt
nes_emulator_py-9.0.0.dist-info/WHEEL
nes_emulator_py-9.0.0.dist-info/licenses/LICENSE
nes_py/__init__.py
nes_py/_rom.py
nes_py/lib_nes_env.cpython-311-x86_64-linux-musl.so
nes_py/_image_viewer.py
nes_py/nes_env.py
nes_py/nes/SConstruct
nes_py/nes/src/picture_bus.cpp
nes_py/nes/src/cpu.cpp
nes_py/nes/src/main_bus.cpp
nes_py/nes/src/emulator.cpp
nes_py/nes/src/lib_nes_env.cpp
nes_py/nes/src/cartridge.cpp
nes_py/nes/src/ppu.cpp
nes_py/nes/src/controller.cpp
nes_py/nes/src/mappers/mapper_NROM.cpp
nes_py/nes/src/mappers/mapper_CNROM.cpp
nes_py/nes/src/mappers/mapper_UxROM.cpp
nes_py/nes/src/mappers/mapper_SxROM.cpp
nes_py/nes/include/picture_bus.hpp
nes_py/nes/include/main_bus.hpp
nes_py/nes/include/mapper_factory.hpp
nes_py/nes/include/common.hpp
nes_py/nes/include/cpu.hpp
nes_py/nes/include/emulator.hpp
nes_py/nes/include/palette.hpp
nes_py/nes/include/mapper.hpp
nes_py/nes/include/cpu_opcodes.hpp
nes_py/nes/include/cartridge.hpp
nes_py/nes/include/controller.hpp
nes_py/nes/include/ppu.hpp
nes_py/nes/include/log.hpp
nes_py/nes/include/mappers/mapper_NROM.hpp
nes_py/nes/include/mappers/mapper_SxROM.hpp
nes_py/nes/include/mappers/mapper_UxROM.hpp
nes_py/nes/include/mappers/mapper_CNROM.hpp
