Metadata-Version: 2.4
Name: nes-emulator-py
Version: 9.0.0
Summary: An NES Emulator and OpenAI Gym interface
Home-page: https://github.com/Kautenja/nes-py
Author: Christian Kauten
Author-email: Christian Kauten <kautencreations@gmail.com>
License: MIT
Project-URL: Homepage, https://github.com/Kautenja/nes-py
Project-URL: Repository, https://github.com/Kautenja/nes-py
Project-URL: Issues, https://github.com/Kautenja/nes-py/issues
Keywords: NES,Emulator,OpenAI-Gym
Classifier: Development Status :: 5 - Production/Stable
Classifier: Intended Audience :: Developers
Classifier: Intended Audience :: Science/Research
Classifier: License :: OSI Approved :: MIT License
Classifier: Operating System :: MacOS :: MacOS X
Classifier: Operating System :: POSIX :: Linux
Classifier: Operating System :: Microsoft :: Windows
Classifier: Programming Language :: C++
Classifier: Programming Language :: Python :: 3 :: Only
Classifier: Programming Language :: Python :: 3.11
Classifier: Programming Language :: Python :: 3.12
Classifier: Topic :: Games/Entertainment
Classifier: Topic :: Software Development :: Libraries :: Python Modules
Classifier: Topic :: System :: Emulators
Requires-Python: >=3.11
License-File: LICENSE
Requires-Dist: gymnasium>=0.28.0
Requires-Dist: numpy>=1.21.0
Requires-Dist: pyglet<=2.0.10,>=1.4.0
Requires-Dist: tqdm>=4.48.2
Dynamic: author
Dynamic: home-page
Dynamic: license-file
Dynamic: requires-python
